{
  "frameeffect": {
    "layer": 1,
    "scale": [
      0.28,
      0.3,
      1
    ],
    "shuffle": false,
    "depth_test": true,
    "frame_color": [
      [
        1,
        1,
        1,
        1
      ],
      [
        1,
        1,
        1,
        1
      ],
      [
        1,
        1,
        1,
        1
      ],
      [
        1,
        1,
        1,
        1
      ],
      [
        1,
        1,
        1,
        1
      ],
      [
        1,
        1,
        1,
        1
      ],
      [
        1,
        1,
        1,
        1
      ],
      [
        1,
        1,
        1,
        1
      ],
      [
        1,
        1,
        1,
        1
      ],
      [
        1,
        1,
        1,
        1
      ],
      [
        1,
        1,
        1,
        1
      ],
      [
        1,
        1,
        1,
        1
      ],
      [
        1,
        1,
        1,
        1
      ],
      [
        1,
        1,
        1,
        1
      ],
      [
        1,
        1,
        1,
        1
      ],
      [
        1,
        1,
        1,
        1
      ],
      [
        1,
        1,
        1,
        1
      ]
    ],
    "first_person_enable": false,
    "texture": "textures/sfxs/2022s3/cs_carnival_armor_mianban",
    "delay": 0.5,
    "fade_distance": 0,
    "lerp_scale": true,
    "tex_repeat_num": [
      1,
      1
    ],
    "fps": 10,
    "delay_in_loop": true,
    "face_camera": false,
    "rot_speed": [
      0,
      0,
      0
    ],
    "cylinder_enable": false,
    "loop": true,
    "blend_mode": 2
  }
}
