{
  "particleeffect": {
    "blend": {
      "name": "add"
    },
    "colorfade": [
      {
        "color": "0.4353 0.9725 1.0000 0.1696",
        "time": "0.00"
      },
      {
        "color": "0.2392 0.6471 1.0000 0.1696",
        "time": "0.20"
      },
      {
        "color": "0.3490 0.2902 1.0000 0.1429",
        "time": "0.46"
      },
      {
        "color": "0.5020 0.0000 1.0000 0.0982",
        "time": "0.69"
      },
      {
        "color": "0.3647 0.0118 0.6549 0.0000",
        "time": "1.00"
      }
    ],
    "dampingforce": {
      "value": "3.0"
    },
    "direction": {
      "max": "-1.0 0.0 0.0",
      "min": "-0.05 0.0 0.0",
      "value": "Direction"
    },
    "emissionrate": {
      "max": "30.0",
      "min": "20.0"
    },
    "emitterScaleCurve": [],
    "emitterscale": [],
    "emittersize": {
      "value": "0.0 0.0 0.0"
    },
    "emittertype": {
      "value": "Box"
    },
    "faceCameraMode": {
      "value": "Horizontal"
    },
    "numparticles": {
      "value": "20"
    },
    "particlesize": {
      "max": "1.2 0.7",
      "min": "0.8 0.6"
    },
    "relative": {
      "enable": "false"
    },
    "rotationRange": {
      "max": "0.0 0.0 0.0",
      "min": "0.0 0.0 360.0"
    },
    "rotationSpeedRange": {
      "max": "0.0 0.0 0.0",
      "min": "0.0 0.0 -1.0"
    },
    "texture": {
      "name": "textures/sfxs/2023s3/cs_atlan_skin_Smoke05"
    },
    "thickness": {
      "value": "0.0"
    },
    "timetolive": {
      "max": "1.0",
      "min": "0.7"
    },
    "velocity": {
      "max": "3.0",
      "min": "2.0"
    }
  }
}
