{
  "animation": {
    "name": "Take 001",
    "ID": "UANI",
    "length": 3.333333,
    "trackSize": 35,
    "tracks": [
      {
        "bone": "Bone002",
        "chanelMask": 7,
        "keyFramesSize": 3,
        "keyframes": [
          {
            "time": 0,
            "pos": [
              6.155189,
              -0.000001,
              11.439479
            ],
            "quaternion": [
              0.5,
              0.499999,
              0.5,
              -0.499999
            ],
            "scale": [
              0.001732,
              0.001,
              0.000268
            ]
          },
          {
            "time": 1.666666,
            "pos": [
              6.155189,
              -0.000001,
              11.439479
            ],
            "quaternion": [
              -0.630543,
              0.630543,
              -0.320023,
              -0.320023
            ],
            "scale": [
              0.002,
              0.002,
              0.002
            ]
          },
          {
            "time": 3.333333,
            "pos": [
              6.155189,
              -0.000001,
              11.439479
            ],
            "quaternion": [
              -0.630543,
              0.630543,
              -0.320023,
              -0.320023
            ],
            "scale": [
              0.001732,
              0.001,
              0.000268
            ]
          }
        ]
      },
      {
        "bone": "Bone137",
        "chanelMask": 3,
        "keyFramesSize": 1,
        "keyframes": [
          {
            "time": 0,
            "pos": [
              2.378422,
              -0.763758,
              0.000001
            ],
            "quaternion": [
              -0.213746,
              -0.976889,
              -7.934710879453633e-7,
              -1.2886847855497763e-7
            ],
            "scale": [
              1,
              1,
              1
            ]
          }
        ]
      },
      {
        "bone": "Bone138",
        "chanelMask": 3,
        "keyFramesSize": 1,
        "keyframes": [
          {
            "time": 0,
            "pos": [
              3.694855,
              -0.339255,
              0
            ],
            "quaternion": [
              -0.999925,
              -0.012204,
              2.378674111014334e-7,
              0
            ],
            "scale": [
              1,
              1,
              1
            ]
          }
        ]
      },
      {
        "bone": "Bone139",
        "chanelMask": 3,
        "keyFramesSize": 1,
        "keyframes": [
          {
            "time": 0,
            "pos": [
              -0.931882,
              0.789072,
              -3.834364
            ],
            "quaternion": [
              -0.126155,
              -0.147181,
              -0.675715,
              0.711218
            ],
            "scale": [
              1,
              1,
              1
            ]
          }
        ]
      },
      {
        "bone": "Bone140",
        "chanelMask": 3,
        "keyFramesSize": 1,
        "keyframes": [
          {
            "time": 0,
            "pos": [
              0.444109,
              -1.440773,
              -0.091165
            ],
            "quaternion": [
              0.032339,
              0.000967,
              0.013156,
              0.999389
            ],
            "scale": [
              1,
              1,
              1
            ]
          }
        ]
      },
      {
        "bone": "Bone141",
        "chanelMask": 1,
        "keyFramesSize": 1,
        "keyframes": [
          {
            "time": 0,
            "pos": [
              1.353646,
              -1.163607,
              -0.084582
            ],
            "quaternion": [
              0,
              0,
              0,
              1
            ],
            "scale": [
              1,
              1,
              1
            ]
          }
        ]
      },
      {
        "bone": "Bone142",
        "chanelMask": 3,
        "keyFramesSize": 1,
        "keyframes": [
          {
            "time": 0,
            "pos": [
              -0.939283,
              0.808622,
              4.03773
            ],
            "quaternion": [
              -0.708203,
              0.677724,
              0.162439,
              0.112918
            ],
            "scale": [
              1,
              1,
              1
            ]
          }
        ]
      },
      {
        "bone": "Bone143",
        "chanelMask": 3,
        "keyFramesSize": 1,
        "keyframes": [
          {
            "time": 0,
            "pos": [
              0.542965,
              1.321946,
              -0.104363
            ],
            "quaternion": [
              0.018364,
              -0.002189,
              -0.034116,
              0.999246
            ],
            "scale": [
              1,
              1,
              1
            ]
          }
        ]
      },
      {
        "bone": "Bone144",
        "chanelMask": 3,
        "keyFramesSize": 1,
        "keyframes": [
          {
            "time": 0,
            "pos": [
              1.198294,
              1.273077,
              -0.198764
            ],
            "quaternion": [
              0.005791,
              -0.008757,
              0.013377,
              0.999855
            ],
            "scale": [
              1,
              1,
              1
            ]
          }
        ]
      },
      {
        "bone": "Bone146",
        "chanelMask": 3,
        "keyFramesSize": 1,
        "keyframes": [
          {
            "time": 0,
            "pos": [
              1.066537,
              -1.145458,
              -1.811116
            ],
            "quaternion": [
              -0.631708,
              0.336459,
              0.358718,
              0.599216
            ],
            "scale": [
              1,
              1,
              1
            ]
          }
        ]
      },
      {
        "bone": "Bone147",
        "chanelMask": 3,
        "keyFramesSize": 1,
        "keyframes": [
          {
            "time": 0,
            "pos": [
              2.450392,
              -1.480859,
              0.136123
            ],
            "quaternion": [
              0,
              1.144936803143537e-7,
              -0.782901,
              0.622145
            ],
            "scale": [
              1,
              1,
              1
            ]
          }
        ]
      },
      {
        "bone": "Bone148",
        "chanelMask": 1,
        "keyFramesSize": 1,
        "keyframes": [
          {
            "time": 0,
            "pos": [
              0.446625,
              -1.137256,
              -1.995373
            ],
            "quaternion": [
              0,
              0,
              0,
              1
            ],
            "scale": [
              1,
              1,
              1
            ]
          }
        ]
      },
      {
        "bone": "Bone149",
        "chanelMask": 1,
        "keyFramesSize": 1,
        "keyframes": [
          {
            "time": 0,
            "pos": [
              2.950501,
              -1.192193,
              0.175609
            ],
            "quaternion": [
              0,
              0,
              0,
              1
            ],
            "scale": [
              1,
              1,
              1
            ]
          }
        ]
      },
      {
        "bone": "Bone150",
        "chanelMask": 1,
        "keyFramesSize": 1,
        "keyframes": [
          {
            "time": 0,
            "pos": [
              1.395907,
              -0.270799,
              -0.287092
            ],
            "quaternion": [
              0,
              0,
              0,
              1
            ],
            "scale": [
              1,
              1,
              1
            ]
          }
        ]
      },
      {
        "bone": "Bone151",
        "chanelMask": 3,
        "keyFramesSize": 1,
        "keyframes": [
          {
            "time": 0,
            "pos": [
              4.70401,
              0.318677,
              0
            ],
            "quaternion": [
              0.02121,
              0.045376,
              -0.422928,
              0.904777
            ],
            "scale": [
              1,
              1,
              1
            ]
          }
        ]
      },
      {
        "bone": "Bone152",
        "chanelMask": 1,
        "keyFramesSize": 1,
        "keyframes": [
          {
            "time": 0,
            "pos": [
              0.446578,
              -1.242012,
              -1.344859
            ],
            "quaternion": [
              0,
              0,
              0,
              1
            ],
            "scale": [
              1,
              1,
              1
            ]
          }
        ]
      },
      {
        "bone": "Bone153",
        "chanelMask": 3,
        "keyFramesSize": 1,
        "keyframes": [
          {
            "time": 0,
            "pos": [
              0.414703,
              -1.177325,
              1.940479
            ],
            "quaternion": [
              -0.987703,
              -0.156335,
              0,
              0
            ],
            "scale": [
              1,
              1,
              1
            ]
          }
        ]
      },
      {
        "bone": "Bone154",
        "chanelMask": 3,
        "keyFramesSize": 1,
        "keyframes": [
          {
            "time": 0,
            "pos": [
              3.065948,
              1.21928,
              -0.07139
            ],
            "quaternion": [
              -0.992273,
              -0.011702,
              -0.123505,
              0.001456
            ],
            "scale": [
              1,
              1,
              1
            ]
          }
        ]
      },
      {
        "bone": "Bone155",
        "chanelMask": 3,
        "keyFramesSize": 1,
        "keyframes": [
          {
            "time": 0,
            "pos": [
              1.474768,
              -0.230702,
              0.182945
            ],
            "quaternion": [
              0.086401,
              -0.088262,
              -0.694174,
              0.70913
            ],
            "scale": [
              1,
              1,
              1
            ]
          }
        ]
      },
      {
        "bone": "Bone156",
        "chanelMask": 3,
        "keyFramesSize": 1,
        "keyframes": [
          {
            "time": 0,
            "pos": [
              4.719841,
              0.300582,
              0
            ],
            "quaternion": [
              -0.0265,
              -0.058393,
              -0.412411,
              0.908738
            ],
            "scale": [
              1,
              1,
              1
            ]
          }
        ]
      },
      {
        "bone": "Bone157",
        "chanelMask": 3,
        "keyFramesSize": 1,
        "keyframes": [
          {
            "time": 0,
            "pos": [
              0.425487,
              1.368929,
              -1.24482
            ],
            "quaternion": [
              0.009231,
              -0.223621,
              -0.004198,
              0.974623
            ],
            "scale": [
              1,
              1,
              1
            ]
          }
        ]
      },
      {
        "bone": "Bone158",
        "chanelMask": 3,
        "keyFramesSize": 1,
        "keyframes": [
          {
            "time": 0,
            "pos": [
              0.409058,
              1.914479,
              0
            ],
            "quaternion": [
              -0.728998,
              -0.684514,
              0,
              0
            ],
            "scale": [
              1,
              1,
              1
            ]
          }
        ]
      },
      {
        "bone": "Bone159",
        "chanelMask": 3,
        "keyFramesSize": 1,
        "keyframes": [
          {
            "time": 0,
            "pos": [
              1.873471,
              1.605284,
              -0.143066
            ],
            "quaternion": [
              -0.72292,
              -0.690931,
              0,
              0
            ],
            "scale": [
              1,
              1,
              1
            ]
          }
        ]
      },
      {
        "bone": "Bone161",
        "chanelMask": 3,
        "keyFramesSize": 1,
        "keyframes": [
          {
            "time": 0,
            "pos": [
              2.553633,
              2.68364,
              0.000015
            ],
            "quaternion": [
              0.000002,
              0,
              2.3841860752327193e-7,
              1
            ],
            "scale": [
              1,
              1,
              1
            ]
          }
        ]
      },
      {
        "bone": "Bone162",
        "chanelMask": 3,
        "keyFramesSize": 1,
        "keyframes": [
          {
            "time": 0,
            "pos": [
              3.494924,
              -0.168095,
              2.268611
            ],
            "quaternion": [
              -1.2364829160560475e-7,
              -1.1240526731626233e-7,
              -0.20813,
              0.978101
            ],
            "scale": [
              1,
              1,
              1
            ]
          }
        ]
      },
      {
        "bone": "Bone163",
        "chanelMask": 1,
        "keyFramesSize": 1,
        "keyframes": [
          {
            "time": 0,
            "pos": [
              3.229588,
              0.00003,
              -7.152556804612686e-7
            ],
            "quaternion": [
              0,
              0,
              0,
              1
            ],
            "scale": [
              1,
              1,
              1
            ]
          }
        ]
      },
      {
        "bone": "Bone165",
        "chanelMask": 1,
        "keyFramesSize": 1,
        "keyframes": [
          {
            "time": 0,
            "pos": [
              3.229588,
              0.00003,
              -7.986789114511339e-7
            ],
            "quaternion": [
              0,
              0,
              0,
              1
            ],
            "scale": [
              1,
              1,
              1
            ]
          }
        ]
      },
      {
        "bone": "Bone166",
        "chanelMask": 3,
        "keyFramesSize": 1,
        "keyframes": [
          {
            "time": 0,
            "pos": [
              3.590446,
              0.423046,
              -9.5367431640625e-7
            ],
            "quaternion": [
              2.3540782478903566e-7,
              0,
              -0.158419,
              0.987371
            ],
            "scale": [
              1,
              1,
              1
            ]
          }
        ]
      },
      {
        "bone": "Bone167",
        "chanelMask": 1,
        "keyFramesSize": 1,
        "keyframes": [
          {
            "time": 0,
            "pos": [
              3.218781,
              -0.242216,
              0
            ],
            "quaternion": [
              0,
              0,
              0,
              1
            ],
            "scale": [
              1,
              1,
              1
            ]
          }
        ]
      },
      {
        "bone": "Bone168",
        "chanelMask": 3,
        "keyFramesSize": 1,
        "keyframes": [
          {
            "time": 0,
            "pos": [
              2.900533,
              -0.699138,
              9.5367431640625e-7
            ],
            "quaternion": [
              -2.3039179097850138e-7,
              -1.0679789852474642e-7,
              -0.707021,
              0.707191
            ],
            "scale": [
              1,
              1,
              1
            ]
          }
        ]
      },
      {
        "bone": "Bone169",
        "chanelMask": 3,
        "keyFramesSize": 1,
        "keyframes": [
          {
            "time": 0,
            "pos": [
              2.498807,
              0.297412,
              -1.493428
            ],
            "quaternion": [
              -0.499999,
              0.5,
              0.5,
              0.5
            ],
            "scale": [
              1,
              1,
              1
            ]
          }
        ]
      },
      {
        "bone": "Bone170",
        "chanelMask": 3,
        "keyFramesSize": 1,
        "keyframes": [
          {
            "time": 0,
            "pos": [
              2.96123,
              -0.194062,
              -0.985378
            ],
            "quaternion": [
              -0.287152,
              0.646175,
              0.646176,
              0.287152
            ],
            "scale": [
              1,
              1,
              1
            ]
          }
        ]
      },
      {
        "bone": "Bone171",
        "chanelMask": 3,
        "keyFramesSize": 1,
        "keyframes": [
          {
            "time": 0,
            "pos": [
              2.503962,
              0.278537,
              1.454831
            ],
            "quaternion": [
              -0.499999,
              -0.499999,
              -0.499999,
              0.5
            ],
            "scale": [
              1,
              1,
              1
            ]
          }
        ]
      },
      {
        "bone": "Bone172",
        "chanelMask": 3,
        "keyFramesSize": 1,
        "keyframes": [
          {
            "time": 0,
            "pos": [
              2.963772,
              -0.214372,
              0.993184
            ],
            "quaternion": [
              0.286345,
              0.646534,
              0.646534,
              -0.286343
            ],
            "scale": [
              1,
              1,
              1
            ]
          }
        ]
      },
      {
        "bone": "Bone183",
        "chanelMask": 3,
        "keyFramesSize": 1,
        "keyframes": [
          {
            "time": 0,
            "pos": [
              7.329442,
              -2.424222,
              -0.000468
            ],
            "quaternion": [
              0.000006,
              0.000019,
              0.214719,
              0.976675
            ],
            "scale": [
              1,
              1,
              1
            ]
          }
        ]
      }
    ]
  }
}
